{"version":"20131101","logo":"http://image.aladin.co.kr/img/header/2011/aladin_logo_new.gif","title":"알라딘 주목할 만한 신간 리스트 - 애니메이션 굿즈","link":"https://www.aladin.co.kr/shop/common/wnew.aspx?NewType=SpecialNew&amp;BranchType=7&amp;CID=115123&amp;partner=openAPI","pubDate":"Thu, 05 Dec 2024 20:56:00 GMT","totalResults":1795,"startIndex":1,"itemsPerPage":10,"query":"QueryType=ITEMNEWSPECIAL;CategoryId=115123","searchCategoryId":115123,"searchCategoryName":"애니메이션 굿즈","item":[{"title":"츠미첸 블루 록 (와플콘 컵 포함 세트) - 1BOX=6개입, 와플콘 포함","link":"http://www.aladin.co.kr/shop/wproduct.aspx?ItemId=353419924&amp;partner=openAPI&amp;start=api","author":"","pubDate":"2025-06-30","description":"","isbn":"F332035684","isbn13":"4535123842993","itemId":353419924,"priceSales":68000,"priceStandard":68000,"mallType":"FOREIGN","stockStatus":"예약판매","mileage":2040,"cover":"https://image.aladin.co.kr/product/35341/99/cover200/f332035684_1.jpg","categoryId":126468,"categoryName":"외국도서>일본 도서>애니메이션 굿즈>피규어","publisher":"メガハウス(MegaHouse)","salesPoint":0,"adult":false,"customerReviewRank":0,"subInfo":{}},{"title":"룩업 TV애니메이션 단다단 오카룬 - 약 110㎜ PVC 도색완료 가동 피규어","link":"http://www.aladin.co.kr/shop/wproduct.aspx?ItemId=353419420&amp;partner=openAPI&amp;start=api","author":"","pubDate":"2025-05-31","description":"","isbn":"F122035684","isbn13":"4535123843099","itemId":353419420,"priceSales":44000,"priceStandard":44000,"mallType":"FOREIGN","stockStatus":"예약판매","mileage":1320,"cover":"https://image.aladin.co.kr/product/35341/94/cover200/f122035684_1.jpg","categoryId":126468,"categoryName":"외국도서>일본 도서>애니메이션 굿즈>피규어","publisher":"メガハウス","salesPoint":0,"adult":false,"customerReviewRank":0,"subInfo":{}},{"title":"룩업 블루 록 치기리 효마 2차전형ver. - 약 110㎜ PVC제 도색완료 가동 피규어","link":"http://www.aladin.co.kr/shop/wproduct.aspx?ItemId=353414588&amp;partner=openAPI&amp;start=api","author":"","pubDate":"2025-06-30","description":"","isbn":"F452035683","isbn13":"4535123842788","itemId":353414588,"priceSales":40000,"priceStandard":40000,"mallType":"FOREIGN","stockStatus":"예약판매","mileage":1200,"cover":"https://image.aladin.co.kr/product/35341/45/cover200/f452035683_1.jpg","categoryId":126468,"categoryName":"외국도서>일본 도서>애니메이션 굿즈>피규어","publisher":"メガハウス","salesPoint":0,"adult":false,"customerReviewRank":0,"subInfo":{}},{"title":"룩업 NARUTO-나루토-질풍전 나미카제 미나토 - 약110mm PVC 도색완료 완성품 피규어","link":"http://www.aladin.co.kr/shop/wproduct.aspx?ItemId=353414051&amp;partner=openAPI&amp;start=api","author":"","pubDate":"2025-06-30","description":"","isbn":"F362035683","isbn13":"4535123842658","itemId":353414051,"priceSales":40000,"priceStandard":40000,"mallType":"FOREIGN","stockStatus":"예약판매","mileage":1200,"cover":"https://image.aladin.co.kr/product/35341/40/cover200/f362035683_1.jpg","categoryId":126468,"categoryName":"외국도서>일본 도서>애니메이션 굿즈>피규어","publisher":"メガハウス(MegaHouse)","salesPoint":0,"adult":false,"customerReviewRank":0,"subInfo":{}},{"title":"룩업 은혼 카구라 - 약110mm PVC 도색완료 완성품 피규어","link":"http://www.aladin.co.kr/shop/wproduct.aspx?ItemId=353412862&amp;partner=openAPI&amp;start=api","author":"","pubDate":"2025-05-31","description":"","isbn":"F952035683","isbn13":"4535123842689","itemId":353412862,"priceSales":42000,"priceStandard":42000,"mallType":"FOREIGN","stockStatus":"예약판매","mileage":1260,"cover":"https://image.aladin.co.kr/product/35341/28/cover200/f952035683_1.jpg","categoryId":126468,"categoryName":"외국도서>일본 도서>애니메이션 굿즈>피규어","publisher":"メガハウス(MegaHouse)","salesPoint":0,"adult":false,"customerReviewRank":0,"seriesInfo":{"seriesId":1179519,"seriesLink":"http://www.aladin.co.kr/shop/common/wseriesitem.aspx?SRID=1179519&amp;partner=openAPI","seriesName":"룩업 은혼 4"},"subInfo":{}},{"title":"룩업 주술회전 쵸소우 - 약 110mm PVC 채색완료 가동 피규어","link":"http://www.aladin.co.kr/shop/wproduct.aspx?ItemId=353412562&amp;partner=openAPI&amp;start=api","author":"","pubDate":"2025-06-30","description":"","isbn":"F702035682","isbn13":"4535123843037","itemId":353412562,"priceSales":40000,"priceStandard":40000,"mallType":"FOREIGN","stockStatus":"예약판매","mileage":1200,"cover":"https://image.aladin.co.kr/product/35341/25/cover200/f702035682_1.jpg","categoryId":126468,"categoryName":"외국도서>일본 도서>애니메이션 굿즈>피규어","publisher":"メガハウス(MegaHouse)","salesPoint":0,"adult":false,"customerReviewRank":0,"subInfo":{}},{"title":"아크릴 스탠드 가끔씩 툭하고 러시아어로 부끄러워하는 옆자리의 아랴 양 02 마샤 나이트 풀ver. (描き下ろし일러스트)","link":"http://www.aladin.co.kr/shop/wproduct.aspx?ItemId=353411460&amp;partner=openAPI&amp;start=api","author":"","pubDate":"2025-03-31","description":"","isbn":"F122035682","isbn13":"4582793508230","itemId":353411460,"priceSales":20290,"priceStandard":22550,"mallType":"FOREIGN","stockStatus":"예약판매","mileage":610,"cover":"https://image.aladin.co.kr/product/35341/14/cover200/f122035682_1.jpg","categoryId":126472,"categoryName":"외국도서>일본 도서>애니메이션 굿즈>잡화","publisher":"A3","salesPoint":0,"adult":false,"customerReviewRank":0,"subInfo":{}},{"title":"가끔씩 툭하고 러시아어로 부끄러워하는 옆자리의 아랴 양 스테인드 글라스풍 아크릴 스탠드 스오우 유키 드레스ver.","link":"http://www.aladin.co.kr/shop/wproduct.aspx?ItemId=353411023&amp;partner=openAPI&amp;start=api","author":"","pubDate":"2025-02-28","description":"","isbn":"F932035682","isbn13":"4942330341728","itemId":353411023,"priceSales":19680,"priceStandard":21870,"mallType":"FOREIGN","stockStatus":"예약판매","mileage":600,"cover":"https://image.aladin.co.kr/product/35341/10/cover200/f932035682_1.jpg","categoryId":126472,"categoryName":"외국도서>일본 도서>애니메이션 굿즈>잡화","publisher":"KADOKAWA","salesPoint":0,"adult":false,"customerReviewRank":0,"subInfo":{}},{"title":"TV애니메이션 가끔씩 툭하고 러시아어로 부끄러워하는 옆자리의 아랴 양 유키 Ani-Art BIG 아크릴 스탠드","link":"http://www.aladin.co.kr/shop/wproduct.aspx?ItemId=353410307&amp;partner=openAPI&amp;start=api","author":"","pubDate":"2025-03-31","description":"","isbn":"F702035681","isbn13":"4571622801598","itemId":353410307,"priceSales":22140,"priceStandard":24600,"mallType":"FOREIGN","stockStatus":"예약판매","mileage":670,"cover":"https://image.aladin.co.kr/product/35341/3/cover200/f702035681_1.jpg","categoryId":126472,"categoryName":"외국도서>일본 도서>애니메이션 굿즈>잡화","publisher":"アルマビアンカ","salesPoint":0,"adult":false,"customerReviewRank":0,"subInfo":{}},{"title":"TV애니메이션 블루 록 바치라 메구루 응원 키링 부착 합성피혁 키홀더","link":"http://www.aladin.co.kr/shop/wproduct.aspx?ItemId=353409534&amp;partner=openAPI&amp;start=api","author":"","pubDate":"2025-03-31","description":"","isbn":"F412035681","isbn13":"4571622735046","itemId":353409534,"priceSales":18450,"priceStandard":20500,"mallType":"FOREIGN","stockStatus":"예약판매","mileage":560,"cover":"https://image.aladin.co.kr/product/35340/95/cover200/f412035681_1.jpg","categoryId":126472,"categoryName":"외국도서>일본 도서>애니메이션 굿즈>잡화","publisher":"アルマビアンカ","salesPoint":0,"adult":false,"customerReviewRank":0,"subInfo":{}}]}