[{"link":"https://blog.aladin.co.kr/764566121/15972938","imgUrl":"https://image.aladin.co.kr/product/35086/44/covermini/893644879x_2.jpg","author":"숸","title":"<팥빙수 눈사람 펑펑 1>","desc":"얼음으로 만든 안경을 만들어 파는 눈사람이 주인공인 이야기예요. 통통 튀는 듯한 그림과 문장이 무척 귀여워요. 소재가 독특한데, 귀여운 그림과 글로 잘 녹여내신 것 같습니다!! 2권도 궁금해요.ㅎㅎ"},{"link":"https://blog.aladin.co.kr/785049131/15972934","imgUrl":"https://image.aladin.co.kr/product/35049/98/covermini/k142934188_1.jpg","author":"행복","title":"<식단 혁명>","desc":"케톤제닉 다이어트를 가장 논리저으로 잘 설명한 채."},{"link":"https://blog.aladin.co.kr/702429133/15972933","imgUrl":"https://image.aladin.co.kr/product/34942/12/covermini/k792934464_1.jpg","author":"Abbo","title":"<엘리펀트 헤드>","desc":"시라이 도모유키 책은 절대 실망시키지 않음. 정말 최고였다"},{"link":"https://blog.aladin.co.kr/735362206/15972932","imgUrl":"https://image.aladin.co.kr/img/19book_65cover.jpg","author":"merryxmas00","title":"<[세트] 불가항력 (총3권/완결)>","desc":"무난하게 읽었어요"},{"link":"https://blog.aladin.co.kr/727202158/15972931","imgUrl":"https://image.aladin.co.kr/product/35117/48/covermini/e042534706_1.jpg","author":"coco","title":"<[루비] 등대지기와 갈매기 아이 1부>","desc":"2권보고싶어지는 내용"},{"link":"https://blog.aladin.co.kr/746948108/15972929","imgUrl":"https://image.aladin.co.kr/img/19book_65cover.jpg","author":"링리이링링","title":"<[세트] [BL] 스토킹 다이어리 (총4권/완결)>","desc":"재밌게 읽었어요"},{"link":"https://blog.aladin.co.kr/715738195/15972925","imgUrl":"https://image.aladin.co.kr/product/271/65/covermini/8958622598_3.jpg","author":"히카루","title":"<뇌, 생각의 출현>","desc":"저자에 대해서 극찬을 듣고 읽었는데 배경지식이 없어 그런지 어려웠음."},{"link":"https://blog.aladin.co.kr/791196191/15972919","imgUrl":"https://image.aladin.co.kr/img/19book_65cover.jpg","author":"Serenity","title":"<[고화질] [BL] 너는 사랑스러운 라이어 보이>","desc":"덩치차이 좋다 그림체 좋다 캐릭터들 귀엽다"},{"link":"https://blog.aladin.co.kr/781790113/15972910","imgUrl":"https://image.aladin.co.kr/img/19book_65cover.jpg","author":"lyshoo","title":"<[BL] 마이 엔젤 (My Angel) (동양풍 오메가버스 AU 외전)>","desc":"재밌었어요. 잘 봤습니다."},{"link":"https://blog.aladin.co.kr/763423116/15972909","imgUrl":"https://image.aladin.co.kr/product/35117/48/covermini/e042534706_1.jpg","author":"잼잼","title":"<[루비] 등대지기와 갈매기 아이 1부>","desc":"와우! 1부는 행복한 동화 같군요. 다음권은 어떻게 진행될지 궁금합니다."}]