{"version":"20131101","logo":"http://image.aladin.co.kr/img/header/2011/aladin_logo_new.gif","title":"알라딘 베스트셀러 리스트 - 문구","link":"https://www.aladin.co.kr/shop/common/wbest.aspx?BestType=Bestseller&amp;BranchType=5&amp;CID=183641&amp;Year=2024&amp;Month=11&amp;Week=2&amp;partner=openAPI","pubDate":"Sat, 16 Nov 2024 20:51:31 GMT","totalResults":1000,"startIndex":1,"itemsPerPage":10,"query":"QueryType=BESTSELLER;CategoryId=183641;Year=2024;Month=11;Week=2","searchCategoryId":183641,"searchCategoryName":"문구","item":[{"title":"[문화연필] 세라믹샤프심EX 0.5mm - HB","link":"http://www.aladin.co.kr/shop/wproduct.aspx?ItemId=278017516&amp;partner=openAPI&amp;start=api","author":"","pubDate":"2021-08-18","description":"","isbn":"G102430331","isbn13":"8801006511147","itemId":278017516,"priceSales":300,"priceStandard":300,"mallType":"GIFT","stockStatus":"","mileage":0,"cover":"https://image.aladin.co.kr/product/27801/75/cover200/g102430331_1.jpg","categoryId":184543,"categoryName":"알라딘굿즈>문구>필기구>연필·샤프","publisher":"","salesPoint":412689,"adult":false,"customerReviewRank":9,"bestRank":1},{"title":"글자를 가리지 않는 스티키 북마크 (40매) - 옐로우","link":"http://www.aladin.co.kr/shop/wproduct.aspx?ItemId=342157013&amp;partner=openAPI&amp;start=api","author":"","pubDate":"2024-06-27","description":"","isbn":"G702431343","isbn13":"G000702431343","itemId":342157013,"priceSales":2800,"priceStandard":2800,"mallType":"GIFT","stockStatus":"","mileage":0,"cover":"https://image.aladin.co.kr/product/34215/70/cover200/g702431343_1.jpg","categoryId":184539,"categoryName":"알라딘굿즈>문구>메모지·스티키>스티키·인덱스","publisher":"","salesPoint":99795,"adult":false,"customerReviewRank":10,"bestRank":2},{"title":"우주 홀로그램 엽서와 우표 세트 (봉투 포함) - 달","link":"http://www.aladin.co.kr/shop/wproduct.aspx?ItemId=346791899&amp;partner=openAPI&amp;start=api","author":"","pubDate":"2024-09-10","description":"","isbn":"G452431059","isbn13":"G000452431059","itemId":346791899,"priceSales":3200,"priceStandard":3200,"mallType":"GIFT","stockStatus":"","mileage":0,"cover":"https://image.aladin.co.kr/product/34679/18/cover200/g452431059.jpg","categoryId":184482,"categoryName":"알라딘굿즈>문구>엽서·우표","publisher":"","salesPoint":57980,"adult":false,"customerReviewRank":0,"bestRank":3},{"title":"본투리드 초저점도 3색 볼펜 0.7mm - 알베르 카뮈 그레이(1자루)","link":"http://www.aladin.co.kr/shop/wproduct.aspx?ItemId=312244903&amp;partner=openAPI&amp;start=api","author":"","pubDate":"2023-02-28","description":"","isbn":"G392431795","isbn13":"8801006275162","itemId":312244903,"priceSales":1500,"priceStandard":1500,"mallType":"GIFT","stockStatus":"","mileage":0,"cover":"https://image.aladin.co.kr/product/31224/49/cover200/g392431795_1.jpg","categoryId":184541,"categoryName":"알라딘굿즈>문구>필기구>볼펜·만년필","publisher":"","salesPoint":287145,"adult":false,"customerReviewRank":8,"bestRank":4},{"title":"전통 문양 마스킹 테이프 - 고양이 나전 홀로그램","link":"http://www.aladin.co.kr/shop/wproduct.aspx?ItemId=343972732&amp;partner=openAPI&amp;start=api","author":"","pubDate":"2024-07-31","description":"","isbn":"G472431645","isbn13":"G000472431645","itemId":343972732,"priceSales":4000,"priceStandard":4000,"mallType":"GIFT","stockStatus":"","mileage":0,"cover":"https://image.aladin.co.kr/product/34397/27/cover200/g472431645.jpg","categoryId":184546,"categoryName":"알라딘굿즈>문구>스티커·테이프>마스킹테이프","publisher":"","salesPoint":91130,"adult":false,"customerReviewRank":10,"bestRank":5,"seriesInfo":{"seriesId":1209132,"seriesLink":"http://www.aladin.co.kr/shop/common/wseriesitem.aspx?SRID=1209132&amp;partner=openAPI","seriesName":"전통 문양 굿즈 3"}},{"title":"본투리드 볼펜 (유성) - 0.5_블랙 (1자루)","link":"http://www.aladin.co.kr/shop/wproduct.aspx?ItemId=289983945&amp;partner=openAPI&amp;start=api","author":"","pubDate":"2022-02-28","description":"","isbn":"G352430351","isbn13":"2050005002903","itemId":289983945,"priceSales":1200,"priceStandard":1200,"mallType":"GIFT","stockStatus":"","mileage":0,"cover":"https://image.aladin.co.kr/product/28998/39/cover200/g352430351.jpg","categoryId":184541,"categoryName":"알라딘굿즈>문구>필기구>볼펜·만년필","publisher":"","salesPoint":214666,"adult":false,"customerReviewRank":7,"bestRank":6},{"title":"[문화연필] 네임펜 - 빨강","link":"http://www.aladin.co.kr/shop/wproduct.aspx?ItemId=302671081&amp;partner=openAPI&amp;start=api","author":"","pubDate":"2022-10-06","description":"","isbn":"G142431575","isbn13":"8801006722666","itemId":302671081,"priceSales":500,"priceStandard":500,"mallType":"GIFT","stockStatus":"","mileage":0,"cover":"https://image.aladin.co.kr/product/30267/10/cover200/g142431575_1.jpg","categoryId":184542,"categoryName":"알라딘굿즈>문구>필기구>형광펜·색연필·사인펜","publisher":"","salesPoint":125487,"adult":false,"customerReviewRank":10,"bestRank":7},{"title":"스티키 북마크(120매) - 클림트","link":"http://www.aladin.co.kr/shop/wproduct.aspx?ItemId=330674843&amp;partner=openAPI&amp;start=api","author":"","pubDate":"2023-12-19","description":"","isbn":"G172431226","isbn13":"G000172431226","itemId":330674843,"priceSales":2800,"priceStandard":2800,"mallType":"GIFT","stockStatus":"","mileage":0,"cover":"https://image.aladin.co.kr/product/33067/48/cover200/g172431226_1.jpg","categoryId":184539,"categoryName":"알라딘굿즈>문구>메모지·스티키>스티키·인덱스","publisher":"","salesPoint":188792,"adult":false,"customerReviewRank":5,"bestRank":8},{"title":"전통 문양 양장노트 - 고양이 나전 홀로그램","link":"http://www.aladin.co.kr/shop/wproduct.aspx?ItemId=343972496&amp;partner=openAPI&amp;start=api","author":"","pubDate":"2024-07-31","description":"","isbn":"G312431645","isbn13":"G000312431645","itemId":343972496,"priceSales":12000,"priceStandard":12000,"mallType":"GIFT","stockStatus":"","mileage":0,"cover":"https://image.aladin.co.kr/product/34397/24/cover200/g312431645.jpg","categoryId":184534,"categoryName":"알라딘굿즈>문구>노트>양장노트","publisher":"","salesPoint":77555,"adult":false,"customerReviewRank":8,"bestRank":9,"seriesInfo":{"seriesId":1209132,"seriesLink":"http://www.aladin.co.kr/shop/common/wseriesitem.aspx?SRID=1209132&amp;partner=openAPI","seriesName":"전통 문양 굿즈 4"}},{"title":"[문화연필] 언더라인 에스 - 주황","link":"http://www.aladin.co.kr/shop/wproduct.aspx?ItemId=339256011&amp;partner=openAPI&amp;start=api","author":"","pubDate":"2024-05-08","description":"","isbn":"G732431845","isbn13":"8801006752106","itemId":339256011,"priceSales":300,"priceStandard":300,"mallType":"GIFT","stockStatus":"","mileage":0,"cover":"https://image.aladin.co.kr/product/33925/60/cover200/g712431845_3.jpg","categoryId":184542,"categoryName":"알라딘굿즈>문구>필기구>형광펜·색연필·사인펜","publisher":"","salesPoint":53489,"adult":false,"customerReviewRank":10,"bestRank":10}]}